AppiumSikuliLibrary/__init__.py
AppiumSikuliLibrary/keywords.py
AppiumSikuliLibrary/sikuli.py
AppiumSikuliLibrary/version.py
AppiumSikuliLibrary/lib/AppiumSikuliLibrary.jar
robotframework_AppiumSikuliLibrary-2023.10.11.dist-info/LICENSE.txt
robotframework_AppiumSikuliLibrary-2023.10.11.dist-info/METADATA
robotframework_AppiumSikuliLibrary-2023.10.11.dist-info/WHEEL
robotframework_AppiumSikuliLibrary-2023.10.11.dist-info/top_level.txt
robotframework_AppiumSikuliLibrary-2023.10.11.dist-info/RECORD
