Metadata-Version: 2.1
Name: robotframework-AppiumSikuliLibrary
Version: 2023.10.11
Summary: Appium - Sikuli library for Robot Framework
Home-page: https://github.com/thinhntt/robotframework-AppiumSikuliLibrary
Author: Thinh Nguyen
Author-email: nguyenvanthinh.dnn@gmail.com
License: Apache License 2.0
Keywords: robotframework testing testautomation sikuli UI on PC,Mobile
Platform: any
Classifier: Operating System :: OS Independent
Classifier: Programming Language :: Python
Classifier: Programming Language :: Java
Classifier: Topic :: Software Development :: Testing
License-File: LICENSE.txt
